{
  "CNTS-00133397256": {
    "era": "경성사범",
    "school_name": "경성사범대학 부속중학교",
    "summary": "광복 직후 경성사범대학 부속중학교(현 서울사대부고의 전신)의 신입생 모집 광고."
  },
  "CNTS-00113759045": {
    "era": "부속중학교",
    "school_name": "서울대학교 사범대학 부속중학교",
    "summary": "학생 간 충돌로 무장경관까지 출동한 사건 보도. 남녀공학을 둘러싼 갈등기."
  },
  "CNTS-00088016404": {
    "era": "부속중학교",
    "school_name": "서울대학교 사범대학 부속중학교",
    "summary": "사대부중의 남녀공학 시행을 둘러싼 파장을 다룬 기사."
  },
  "CNTS-00133623780": {
    "era": "부속중학교",
    "school_name": "서울대학교 사범대학 부속중학교",
    "summary": "학부형들이 남녀공학 폐지를 진정했다는 보도."
  },
  "CNTS-00114967424": {
    "era": "부속중학교",
    "school_name": "서울대학교 사범대학 부속중학교",
    "summary": "사대부중 학부형들의 남녀공학제 폐지 건의 보도."
  },
  "CNTS-00088037963": {
    "era": "부속중학교",
    "school_name": "서울대학교 사범대학 부속중학교",
    "summary": "사대부중 기독학생회가 성금을 신문사에 기탁."
  },
  "CNTS-00069070187": {
    "era": "부속중학교",
    "school_name": "서울대학교 사범대학 부속중학교",
    "summary": "남녀공학과 창립 초기 일화를 다룬 '학원 순례' 연재 기사."
  },
  "CNTS-00069083141": {
    "era": "부속중학교",
    "school_name": "국립서울대학교 사범대학 부속중학교",
    "summary": "교명(국립서울대학교 사범대학 부속중학교)이 명기된 기사."
  },
  "CNTS-00069083385": {
    "era": "부속중학교",
    "school_name": "국립서울대학교 사범대학 부속중학교",
    "summary": "교명(국립서울대학교 사범대학 부속중학교)이 명기된 기사."
  },
  "CNTS-00115215409": {
    "era": "부속중학교",
    "school_name": "서울대학교 사범대학 부속중학교",
    "summary": "사대부중 학생들의 국방헌금(비행기 헌납) 모금 보도."
  },
  "CNTS-00069189960": {
    "era": "부속중학교",
    "school_name": "서울대학교 사범대학 부속중학교",
    "summary": "'학생호' 헌납에 사대부중도 칠만원을 모금했다는 보도."
  },
  "CNTS-00108821358": {
    "era": "부속중학교",
    "school_name": "서울대학교 사범대학 부속중학교",
    "summary": "국방헌금 열기 속 사대부중이 칠만원을 모금."
  },
  "CNTS-00133929643": {
    "era": "부속중학교",
    "school_name": "서울대학교 사범대학 부속중학교",
    "summary": "서울사대부중 학생 관련 광고(1951)."
  },
  "CNTS-00133931696": {
    "era": "부속중학교",
    "school_name": "국립서울대학교 사범대학 부속중학교",
    "summary": "한국전쟁 중 게재된 국립서울대학교 사범대학 부속중학교 학생모집요항 광고."
  },
  "CNTS-00133986719": {
    "era": "부속고",
    "school_name": "서울대학교 사범대학 부속고등학교",
    "summary": "세계청년토론회에 사대부고 학생이 참가했다는 소식."
  },
  "CNTS-00131839893": {
    "era": "부속고",
    "school_name": "서울대학교 사범대학 부속고등학교",
    "summary": "중·고 분리 후 '서울대학교 사범대학 부속고등학교' 명칭이 확인되는 광고."
  },
  "CNTS-00132178209": {
    "era": "부속중학교",
    "school_name": "서울대학교 사범대학 부속중학교",
    "summary": "치열한 중학 입시 경쟁 속 서울사대부중 관련 보도."
  },
  "CNTS-00132184425": {
    "era": "부속고",
    "school_name": "서울대학교 사범대학 부속고등학교",
    "summary": "신임 교장 부임에 반대한 서울사대부고 학생들의 동맹휴학(맹휴) 사건."
  },
  "CNTS-00132342286": {
    "era": "부속고",
    "school_name": "서울대학교 사범대학 부속고등학교",
    "summary": "지상 과학전에 소개된 서울사대부고 화학반의 연구 작품."
  },
  "CNTS-00094130458": {
    "era": "경성사범",
    "school_name": "경성사범학교",
    "summary": "1921년 개교한 경성사범학교의 입학식·선서식 거행 소식. 현 서울사대부고의 먼 뿌리에 해당하는 관립 사범학교다."
  },
  "CNTS-00094153678": {
    "era": "경성사범",
    "school_name": "경성사범학교",
    "summary": "졸업생 가운데 조선인은 단 한 명뿐이었음을 전한 기사 — 식민지기 사범교육의 차별적 현실을 드러낸다."
  },
  "CNTS-00094157749": {
    "era": "경성사범",
    "school_name": "경성사범학교",
    "summary": "경성사범학교 보통과 입학시험 문제. 보통과는 뒷날 부속중학교로 이어지는 직접 전신이다."
  },
  "CNTS-00094179807": {
    "era": "경성사범",
    "school_name": "경성사범학교",
    "summary": "경성사범학교 입학 안내 기사."
  },
  "CNTS-00094208488": {
    "era": "경성사범",
    "school_name": "경성사범학교",
    "summary": "백 명 모집에 지원자가 사천 명에 달한 경성사범학교의 높은 입학 경쟁을 전한다."
  },
  "CNTS-00099486732": {
    "era": "경성사범",
    "school_name": "경성사범학교",
    "summary": "경성사범학교 보통과 입학(허가)자 발표."
  },
  "CNTS-00093581087": {
    "era": "경성사범",
    "school_name": "경성사범학교",
    "summary": "경성사범학교 입학시험 합격자 발표(조선중앙일보)."
  },
  "CNTS-00118286378": {
    "era": "경성사범",
    "school_name": "경성사범학교",
    "summary": "경성사범학교 보통과 입학 허가자 명단 발표."
  },
  "CNTS-00118375503": {
    "era": "경성사범",
    "school_name": "경성사범학교",
    "summary": "경성사범학교를 소개한 학교 안내 기사. 칠 년간 헌신한 도변(渡邊) 교장을 함께 다뤘다."
  },
  "CNTS-00114333621": {
    "era": "경성사범",
    "school_name": "경성여자사범학교",
    "summary": "경성여자사범학교 입학시험 합격자 발표."
  },
  "CNTS-00132518014": {
    "era": "경성사범",
    "school_name": "경성사범학교",
    "summary": "광복 직후 경성사범학교가 보결생을 모집한다는 광고."
  },
  "CNTS-00065287840": {
    "era": "경성사범",
    "school_name": "경성사범학교",
    "summary": "광복 직후 경성사범학교 관련 광고(중앙신문)."
  },
  "CNTS-00065297767": {
    "era": "경성사범",
    "school_name": "경성사범대학 부속중학교",
    "summary": "경성사범대학 부속중학교 생도모집 광고(중앙신문). 1946년 9월 서울대 사범대 부속중학교로 이어지는 전환기 자료다."
  },
  "CNTS-00088021236": {
    "era": "경성사범",
    "school_name": "경성사범학교",
    "summary": "경성사범학교 교사(校舍) 이전을 전하는 기사."
  },
  "CNTS-00094214013": {
    "era": "경성사범",
    "school_name": "경성사범학교",
    "summary": ""
  },
  "CNTS-00099488271": {
    "era": "경성사범",
    "school_name": "경성사범학교",
    "summary": ""
  },
  "CNTS-00115167766": {
    "era": "경성사범",
    "school_name": "경성사범학교",
    "summary": ""
  },
  "CNTS-00094157840": {
    "era": "경성사범",
    "school_name": "경성사범학교",
    "summary": ""
  },
  "CNTS-00094183482": {
    "era": "경성사범",
    "school_name": "경성사범학교",
    "summary": ""
  },
  "CNTS-00113727231": {
    "era": "경성사범",
    "school_name": "경성사범학교",
    "summary": ""
  },
  "CNTS-00113727501": {
    "era": "경성사범",
    "school_name": "경성사범학교",
    "summary": ""
  },
  "CNTS-00094212607": {
    "era": "경성사범",
    "school_name": "경성사범학교",
    "summary": ""
  },
  "CNTS-00076949082": {
    "era": "경성사범",
    "school_name": "경성사범학교",
    "summary": ""
  },
  "CNTS-00114156715": {
    "era": "경성사범",
    "school_name": "경성사범학교",
    "summary": ""
  },
  "CNTS-00132368281": {
    "era": "경성사범",
    "school_name": "경성사범학교",
    "summary": ""
  },
  "CNTS-00099305844": {
    "era": "경성사범",
    "school_name": "경성사범학교",
    "summary": ""
  },
  "CNTS-00115121125": {
    "era": "경성사범",
    "school_name": "경성사범학교",
    "summary": ""
  },
  "CNTS-00094477508": {
    "era": "경성사범",
    "school_name": "경성사범학교",
    "summary": ""
  },
  "CNTS-00108859773": {
    "era": "경성사범",
    "school_name": "경성사범학교",
    "summary": ""
  },
  "CNTS-00108859772": {
    "era": "경성사범",
    "school_name": "경성사범학교",
    "summary": ""
  },
  "CNTS-00125910658": {
    "era": "경성사범",
    "school_name": "경성사범학교",
    "summary": ""
  },
  "CNTS-00108951261": {
    "era": "경성사범",
    "school_name": "경성사범학교",
    "summary": ""
  },
  "CNTS-00126012632": {
    "era": "경성사범",
    "school_name": "경성사범학교",
    "summary": ""
  },
  "CNTS-00126014038": {
    "era": "경성사범",
    "school_name": "경성사범학교",
    "summary": ""
  },
  "CNTS-00126014987": {
    "era": "경성사범",
    "school_name": "경성사범학교",
    "summary": ""
  },
  "CNTS-00126015236": {
    "era": "경성사범",
    "school_name": "경성사범학교",
    "summary": ""
  },
  "CNTS-00126015508": {
    "era": "경성사범",
    "school_name": "경성사범학교",
    "summary": ""
  },
  "CNTS-00126017455": {
    "era": "경성사범",
    "school_name": "경성사범학교",
    "summary": ""
  },
  "CNTS-00126018011": {
    "era": "경성사범",
    "school_name": "경성사범학교",
    "summary": ""
  },
  "CNTS-00126018382": {
    "era": "경성사범",
    "school_name": "경성사범학교",
    "summary": ""
  },
  "CNTS-00093581576": {
    "era": "경성사범",
    "school_name": "경성사범학교",
    "summary": ""
  },
  "CNTS-00093581577": {
    "era": "경성사범",
    "school_name": "경성사범학교",
    "summary": ""
  },
  "CNTS-00093583002": {
    "era": "경성사범",
    "school_name": "경성사범학교",
    "summary": ""
  },
  "CNTS-00109117037": {
    "era": "경성사범",
    "school_name": "경성사범학교",
    "summary": ""
  },
  "CNTS-00109117491": {
    "era": "경성사범",
    "school_name": "경성사범학교",
    "summary": ""
  },
  "CNTS-00109117818": {
    "era": "경성사범",
    "school_name": "경성사범학교",
    "summary": ""
  },
  "CNTS-00109118627": {
    "era": "경성사범",
    "school_name": "경성사범학교",
    "summary": ""
  },
  "CNTS-00109118964": {
    "era": "경성사범",
    "school_name": "경성사범학교",
    "summary": ""
  },
  "CNTS-00118382475": {
    "era": "경성사범",
    "school_name": "경성사범학교",
    "summary": ""
  },
  "CNTS-00129032664": {
    "era": "경성사범",
    "school_name": "경성사범학교",
    "summary": ""
  },
  "CNTS-00118386196": {
    "era": "경성사범",
    "school_name": "경성사범학교",
    "summary": ""
  },
  "CNTS-00129035817": {
    "era": "경성사범",
    "school_name": "경성사범학교",
    "summary": ""
  },
  "CNTS-00124442895": {
    "era": "경성사범",
    "school_name": "경성사범학교",
    "summary": ""
  },
  "CNTS-00129258262": {
    "era": "경성사범",
    "school_name": "경성사범학교",
    "summary": ""
  },
  "CNTS-00129259327": {
    "era": "경성사범",
    "school_name": "경성사범학교",
    "summary": ""
  },
  "CNTS-00129260314": {
    "era": "경성사범",
    "school_name": "경성사범학교",
    "summary": ""
  },
  "CNTS-00129261063": {
    "era": "경성사범",
    "school_name": "경성사범학교",
    "summary": ""
  },
  "CNTS-00129261328": {
    "era": "경성사범",
    "school_name": "경성사범학교",
    "summary": ""
  },
  "CNTS-00124971138": {
    "era": "경성사범",
    "school_name": "경성사범학교",
    "summary": ""
  },
  "CNTS-00124992132": {
    "era": "경성사범",
    "school_name": "경성사범학교",
    "summary": ""
  },
  "CNTS-00132518094": {
    "era": "경성사범",
    "school_name": "경성사범학교",
    "summary": ""
  },
  "NAVER-1993090600099119001": {
    "era": "부속고",
    "school_name": "",
    "summary": ""
  },
  "NAVER-1993072400239110023": {
    "era": "부속고",
    "school_name": "",
    "summary": ""
  },
  "NAVER-1994060700239111001": {
    "era": "부속고",
    "school_name": "",
    "summary": ""
  },
  "NAVER-1993090800329112015": {
    "era": "부속고",
    "school_name": "",
    "summary": ""
  },
  "NAVER-1993090800209114022": {
    "era": "부속고",
    "school_name": "",
    "summary": ""
  },
  "NAVER-1993080300289116001": {
    "era": "부속고",
    "school_name": "",
    "summary": ""
  },
  "NAVER-1993122700289107001": {
    "era": "부속고",
    "school_name": "",
    "summary": ""
  },
  "NAVER-1993073100329118019": {
    "era": "부속고",
    "school_name": "",
    "summary": ""
  },
  "NAVER-1993073100239115018": {
    "era": "부속고",
    "school_name": "",
    "summary": ""
  },
  "NAVER-1995042000289105001": {
    "era": "부속고",
    "school_name": "",
    "summary": ""
  },
  "NAVER-1993101100099118001": {
    "era": "부속고",
    "school_name": "",
    "summary": ""
  },
  "NAVER-1998092500209108004": {
    "era": "부속고",
    "school_name": "",
    "summary": ""
  },
  "NAVER-1997012400329114012": {
    "era": "부속고",
    "school_name": "",
    "summary": ""
  },
  "NAVER-1993081700239115007": {
    "era": "부속고",
    "school_name": "",
    "summary": ""
  },
  "NAVER-1994042200289114012": {
    "era": "부속고",
    "school_name": "",
    "summary": ""
  },
  "NAVER-1993123000289106004": {
    "era": "부속고",
    "school_name": "",
    "summary": ""
  },
  "NAVER-1993090100289103009": {
    "era": "부속고",
    "school_name": "",
    "summary": ""
  },
  "NAVER-1993091100239116012": {
    "era": "부속고",
    "school_name": "",
    "summary": ""
  },
  "NAVER-1993080300289111010": {
    "era": "부속고",
    "school_name": "",
    "summary": ""
  },
  "NAVER-1993092700099124001": {
    "era": "부속고",
    "school_name": "",
    "summary": ""
  },
  "NAVER-1993092800329111001": {
    "era": "부속고",
    "school_name": "",
    "summary": ""
  },
  "NAVER-1993122800209110001": {
    "era": "부속고",
    "school_name": "",
    "summary": ""
  },
  "NAVER-1993080400239105001": {
    "era": "부속고",
    "school_name": "",
    "summary": ""
  },
  "NAVER-1993081100289110004": {
    "era": "부속고",
    "school_name": "",
    "summary": ""
  },
  "NAVER-1993080500239103003": {
    "era": "부속고",
    "school_name": "",
    "summary": ""
  },
  "NAVER-1993081100329117020": {
    "era": "부속고",
    "school_name": "",
    "summary": ""
  },
  "NAVER-1993102400239107020": {
    "era": "부속고",
    "school_name": "",
    "summary": ""
  },
  "NAVER-1993071900239109003": {
    "era": "부속고",
    "school_name": "",
    "summary": ""
  },
  "NAVER-1994061400099105004": {
    "era": "부속고",
    "school_name": "",
    "summary": ""
  },
  "NAVER-1993092000239109002": {
    "era": "부속고",
    "school_name": "",
    "summary": ""
  },
  "NAVER-1993091600099119007": {
    "era": "부속고",
    "school_name": "",
    "summary": ""
  },
  "NAVER-1995093000329109001": {
    "era": "부속고",
    "school_name": "",
    "summary": ""
  },
  "NAVER-1993080500289107001": {
    "era": "부속고",
    "school_name": "",
    "summary": ""
  },
  "NAVER-1995110800329109001": {
    "era": "부속고",
    "school_name": "",
    "summary": ""
  },
  "NAVER-1991010600099208001": {
    "era": "부속고",
    "school_name": "",
    "summary": ""
  },
  "NAVER-1994062800099119001": {
    "era": "부속고",
    "school_name": "",
    "summary": ""
  },
  "NAVER-1993122100329104001": {
    "era": "부속고",
    "school_name": "",
    "summary": ""
  },
  "NAVER-1997012300209127012": {
    "era": "부속고",
    "school_name": "",
    "summary": ""
  },
  "NAVER-1994091300329112003": {
    "era": "부속고",
    "school_name": "",
    "summary": ""
  },
  "NAVER-1997062000329118008": {
    "era": "부속고",
    "school_name": "",
    "summary": ""
  },
  "NAVER-1993122500099114009": {
    "era": "부속고",
    "school_name": "",
    "summary": ""
  },
  "NAVER-1993072400239110019": {
    "era": "부속고",
    "school_name": "",
    "summary": ""
  },
  "NAVER-1993072000239113008": {
    "era": "부속고",
    "school_name": "",
    "summary": ""
  },
  "NAVER-1998091400099110001": {
    "era": "부속고",
    "school_name": "",
    "summary": ""
  },
  "NAVER-1992120800099208003": {
    "era": "부속고",
    "school_name": "",
    "summary": ""
  },
  "NAVER-1997030500099111013": {
    "era": "부속고",
    "school_name": "",
    "summary": ""
  },
  "NAVER-1997062000239123035": {
    "era": "부속고",
    "school_name": "",
    "summary": ""
  },
  "NAVER-1999052900099111004": {
    "era": "부속고",
    "school_name": "",
    "summary": ""
  },
  "NAVER-1992120800099208004": {
    "era": "부속고",
    "school_name": "",
    "summary": ""
  },
  "NAVER-1997030500099111014": {
    "era": "부속고",
    "school_name": "",
    "summary": ""
  },
  "NAVER-1963020900200101002": {
    "era": "부속고",
    "school_name": "",
    "summary": ""
  },
  "NAVER-1966020800230201001": {
    "era": "부속고",
    "school_name": "",
    "summary": ""
  },
  "NAVER-1975032000099201005": {
    "era": "부속고",
    "school_name": "",
    "summary": ""
  },
  "NAVER-1987072600239101022": {
    "era": "부속고",
    "school_name": "",
    "summary": ""
  },
  "NAVER-1992021700099223001": {
    "era": "부속고",
    "school_name": "",
    "summary": ""
  },
  "NAVER-1991102100099226001": {
    "era": "부속고",
    "school_name": "",
    "summary": ""
  },
  "NAVER-1995100300099111001": {
    "era": "부속고",
    "school_name": "",
    "summary": ""
  },
  "NAVER-1992110400239102001": {
    "era": "부속고",
    "school_name": "",
    "summary": ""
  },
  "NAVER-1999052900099111001": {
    "era": "부속고",
    "school_name": "",
    "summary": ""
  },
  "NAVER-1966021300239108001": {
    "era": "부속고",
    "school_name": "",
    "summary": ""
  },
  "NAVER-1966020800200103001": {
    "era": "부속고",
    "school_name": "",
    "summary": ""
  },
  "NAVER-1962011300239104001": {
    "era": "부속고",
    "school_name": "",
    "summary": ""
  },
  "NAVER-1963021000239104001": {
    "era": "부속고",
    "school_name": "",
    "summary": ""
  },
  "NAVER-1997090600239111002": {
    "era": "부속고",
    "school_name": "",
    "summary": ""
  },
  "NAVER-1992053000099206008": {
    "era": "부속고",
    "school_name": "",
    "summary": ""
  },
  "NAVER-1995052700099118030": {
    "era": "부속고",
    "school_name": "",
    "summary": ""
  },
  "NAVER-1988121600239108009": {
    "era": "부속고",
    "school_name": "",
    "summary": ""
  },
  "NAVER-1999110800099121012": {
    "era": "부속고",
    "school_name": "",
    "summary": ""
  },
  "NAVER-1994012400239110004": {
    "era": "부속고",
    "school_name": "",
    "summary": ""
  },
  "NAVER-1991042200239119003": {
    "era": "부속고",
    "school_name": "",
    "summary": ""
  },
  "NAVER-1993121400099109006": {
    "era": "부속고",
    "school_name": "",
    "summary": ""
  },
  "NAVER-1995020900099119004": {
    "era": "부속고",
    "school_name": "",
    "summary": ""
  },
  "NAVER-1993092600099105010": {
    "era": "부속고",
    "school_name": "",
    "summary": ""
  },
  "NAVER-1988122100289108004": {
    "era": "부속고",
    "school_name": "",
    "summary": ""
  },
  "NAVER-1997122000099133005": {
    "era": "부속고",
    "school_name": "",
    "summary": ""
  },
  "NAVER-1992102300099208005": {
    "era": "부속고",
    "school_name": "",
    "summary": ""
  },
  "NAVER-1998113000239134002": {
    "era": "부속고",
    "school_name": "",
    "summary": ""
  },
  "NAVER-1999052900099111007": {
    "era": "부속고",
    "school_name": "",
    "summary": ""
  },
  "NAVER-1992070200329106004": {
    "era": "부속고",
    "school_name": "",
    "summary": ""
  },
  "NAVER-1986082100239105003": {
    "era": "부속고",
    "school_name": "",
    "summary": ""
  },
  "NAVER-1997062000099111011": {
    "era": "부속고",
    "school_name": "",
    "summary": ""
  },
  "NAVER-1997012100289127003": {
    "era": "부속고",
    "school_name": "",
    "summary": ""
  },
  "NAVER-1983021900209211024": {
    "era": "부속고",
    "school_name": "",
    "summary": ""
  },
  "NAVER-1993110400099113021": {
    "era": "부속고",
    "school_name": "",
    "summary": ""
  },
  "NAVER-1992010700209222009": {
    "era": "부속고",
    "school_name": "",
    "summary": ""
  },
  "NAVER-1997012900289125019": {
    "era": "부속고",
    "school_name": "",
    "summary": ""
  },
  "NAVER-1987073100099211014": {
    "era": "부속고",
    "school_name": "",
    "summary": ""
  },
  "NAVER-1990022200099211008": {
    "era": "부속고",
    "school_name": "",
    "summary": ""
  },
  "NAVER-1994022500099110009": {
    "era": "부속고",
    "school_name": "",
    "summary": ""
  },
  "NAVER-1990041000099211004": {
    "era": "부속고",
    "school_name": "",
    "summary": ""
  },
  "NAVER-1986071100099211014": {
    "era": "부속고",
    "school_name": "",
    "summary": ""
  },
  "NAVER-1997062000239123020": {
    "era": "부속고",
    "school_name": "",
    "summary": ""
  },
  "NAVER-1998121100099112016": {
    "era": "부속고",
    "school_name": "",
    "summary": ""
  },
  "NAVER-1986101300099210006": {
    "era": "부속고",
    "school_name": "",
    "summary": ""
  },
  "NAVER-1991122300099226013": {
    "era": "부속고",
    "school_name": "",
    "summary": ""
  },
  "NAVER-1997060600099113007": {
    "era": "부속고",
    "school_name": "",
    "summary": ""
  },
  "NAVER-1989012800099207016": {
    "era": "부속고",
    "school_name": "",
    "summary": ""
  },
  "NAVER-1999111600289129025": {
    "era": "부속고",
    "school_name": "",
    "summary": ""
  },
  "NAVER-1993102800099132007": {
    "era": "부속고",
    "school_name": "",
    "summary": ""
  },
  "NAVER-1991102100099226014": {
    "era": "부속고",
    "school_name": "",
    "summary": ""
  },
  "NAVER-1991102800099226018": {
    "era": "부속고",
    "school_name": "",
    "summary": ""
  },
  "NAVER-1999051500099101015": {
    "era": "부속고",
    "school_name": "",
    "summary": ""
  },
  "NAVER-1984090400099211005": {
    "era": "부속고",
    "school_name": "",
    "summary": ""
  },
  "NAVER-1996031900099105010": {
    "era": "부속고",
    "school_name": "",
    "summary": ""
  },
  "NAVER-1977060600329208013": {
    "era": "부속고",
    "school_name": "",
    "summary": ""
  },
  "NAVER-1977042200329208008": {
    "era": "부속고",
    "school_name": "",
    "summary": ""
  },
  "NAVER-1968021900099203018": {
    "era": "부속고",
    "school_name": "",
    "summary": ""
  },
  "NAVER-1977060700209201014": {
    "era": "부속고",
    "school_name": "",
    "summary": ""
  },
  "NAVER-1977060700209201013": {
    "era": "부속고",
    "school_name": "",
    "summary": ""
  },
  "NAVER-1978060300209201013": {
    "era": "부속고",
    "school_name": "",
    "summary": ""
  },
  "NAVER-1977060600209201005": {
    "era": "부속고",
    "school_name": "",
    "summary": ""
  },
  "NAVER-1977062100209207002": {
    "era": "부속고",
    "school_name": "",
    "summary": ""
  },
  "NAVER-1977060700239107005": {
    "era": "부속고",
    "school_name": "",
    "summary": ""
  },
  "NAVER-1977060600329208014": {
    "era": "부속고",
    "school_name": "",
    "summary": ""
  },
  "NAVER-1978052900209208013": {
    "era": "부속고",
    "school_name": "",
    "summary": ""
  },
  "NAVER-1977042200209201012": {
    "era": "부속고",
    "school_name": "",
    "summary": ""
  },
  "NAVER-1977060300209201022": {
    "era": "부속고",
    "school_name": "",
    "summary": ""
  },
  "NAVER-1980123000209201018": {
    "era": "부속고",
    "school_name": "",
    "summary": ""
  },
  "NAVER-1977060600209207001": {
    "era": "부속고",
    "school_name": "",
    "summary": ""
  },
  "NAVER-1967071800239107001": {
    "era": "부속고",
    "school_name": "",
    "summary": ""
  },
  "NAVER-1983101000209211001": {
    "era": "부속고",
    "school_name": "",
    "summary": ""
  },
  "NAVER-1983051900209211001": {
    "era": "부속고",
    "school_name": "",
    "summary": ""
  },
  "NAVER-1987021200209210001": {
    "era": "부속고",
    "school_name": "",
    "summary": ""
  },
  "NAVER-1983070900209212007": {
    "era": "부속고",
    "school_name": "",
    "summary": ""
  },
  "NAVER-1978051700209208013": {
    "era": "부속고",
    "school_name": "",
    "summary": ""
  },
  "NAVER-1977061600209207022": {
    "era": "부속고",
    "school_name": "",
    "summary": ""
  },
  "NAVER-1998090500239126006": {
    "era": "부속고",
    "school_name": "",
    "summary": ""
  },
  "NAVER-1962080100239203034": {
    "era": "부속고",
    "school_name": "",
    "summary": ""
  },
  "NAVER-1978062700209207021": {
    "era": "부속고",
    "school_name": "",
    "summary": ""
  },
  "NAVER-1977061700209207022": {
    "era": "부속고",
    "school_name": "",
    "summary": ""
  },
  "NAVER-1970102900329208002": {
    "era": "부속고",
    "school_name": "",
    "summary": ""
  },
  "NAVER-1977060700239107017": {
    "era": "부속고",
    "school_name": "",
    "summary": ""
  },
  "NAVER-1967071400239103024": {
    "era": "부속고",
    "school_name": "",
    "summary": ""
  },
  "NAVER-1983101800209208003": {
    "era": "부속고",
    "school_name": "",
    "summary": ""
  },
  "NAVER-1968030400329207018": {
    "era": "부속고",
    "school_name": "",
    "summary": ""
  },
  "NAVER-1993110800209127013": {
    "era": "부속고",
    "school_name": "",
    "summary": ""
  },
  "NAVER-1962080200209103005": {
    "era": "부속고",
    "school_name": "",
    "summary": ""
  },
  "NAVER-1970070200239103002": {
    "era": "부속고",
    "school_name": "",
    "summary": ""
  },
  "NAVER-1972091100209205004": {
    "era": "부속고",
    "school_name": "",
    "summary": ""
  },
  "NAVER-1987021300239110005": {
    "era": "부속고",
    "school_name": "",
    "summary": ""
  },
  "NAVER-1967071300329203006": {
    "era": "부속고",
    "school_name": "",
    "summary": ""
  },
  "NAVER-1977051400209208006": {
    "era": "부속고",
    "school_name": "",
    "summary": ""
  },
  "NAVER-1970110600099204002": {
    "era": "부속고",
    "school_name": "",
    "summary": ""
  },
  "NAVER-1978052900209208012": {
    "era": "부속고",
    "school_name": "",
    "summary": ""
  },
  "NAVER-1988071600209208008": {
    "era": "부속고",
    "school_name": "",
    "summary": ""
  },
  "NAVER-1977051600209208018": {
    "era": "부속고",
    "school_name": "",
    "summary": ""
  },
  "NAVER-1967071800329203008": {
    "era": "부속고",
    "school_name": "",
    "summary": ""
  },
  "NAVER-1968021900209203034": {
    "era": "부속고",
    "school_name": "",
    "summary": ""
  },
  "NAVER-1977062100239107016": {
    "era": "부속고",
    "school_name": "",
    "summary": ""
  },
  "NAVER-1977060400209208012": {
    "era": "부속고",
    "school_name": "",
    "summary": ""
  },
  "NAVER-1967081900239103006": {
    "era": "부속고",
    "school_name": "",
    "summary": ""
  },
  "NAVER-1977062000329207012": {
    "era": "부속고",
    "school_name": "",
    "summary": ""
  },
  "NAVER-1967071900239103007": {
    "era": "부속고",
    "school_name": "",
    "summary": ""
  },
  "NAVER-1970103000239107013": {
    "era": "부속고",
    "school_name": "",
    "summary": ""
  },
  "NAVER-1965112900329203015": {
    "era": "부속고",
    "school_name": "",
    "summary": ""
  },
  "NAVER-1970111100239106015": {
    "era": "부속고",
    "school_name": "",
    "summary": ""
  },
  "NAVER-1977060300209208012": {
    "era": "부속고",
    "school_name": "",
    "summary": ""
  },
  "NAVER-1977053100209208017": {
    "era": "부속고",
    "school_name": "",
    "summary": ""
  },
  "NAVER-1978060300209203003": {
    "era": "부속고",
    "school_name": "",
    "summary": ""
  },
  "NAVER-1989092300099203020": {
    "era": "부속고",
    "school_name": "",
    "summary": ""
  },
  "NAVER-1968022000239107021": {
    "era": "부속고",
    "school_name": "",
    "summary": ""
  },
  "NAVER-1992070400099218016": {
    "era": "부속고",
    "school_name": "",
    "summary": ""
  },
  "NAVER-1978051700209208014": {
    "era": "부속고",
    "school_name": "",
    "summary": ""
  },
  "NAVER-1977040100209201014": {
    "era": "부속고",
    "school_name": "",
    "summary": ""
  },
  "NAVER-1967072000329201029": {
    "era": "부속고",
    "school_name": "",
    "summary": ""
  }
}